{
  "home": [
    "A7X02922.jpg",
    "A7X02908.jpg",
    "A7X02875.jpg",
    "A7X02768.jpg",
    "A7X02719.jpg",
    "A7X02624.jpg",
    "A7X02615.jpg",
    "A7X02247.jpg",
    "A7X02241.jpg",
    "A7X01750.jpg",
    "A7X01509.jpg",
    "A7X01012.jpg",
    "A7X00780.jpg",
    "A7X09872.jpg",
    "A7X09679.jpg",
    "A7X08903-Edit.jpg",
    "A7X08615.jpg",
    "A7X08608.jpg",
    "A7X08596.jpg",
    "A7X08009.jpg",
    "A7X07847.jpg",
    "A7X07594.jpg",
    "A7X07090.jpg",
    "A7X06375-Edit.jpg",
    "A7X06339.jpg",
    "A7X06117-Edit.jpg",
    "A7X05898-Edit.jpg",
    "A7X05228.jpg",
    "A7X05085-Edit.jpg",
    "A7X04429-Edit.jpg",
    "A7X04419.jpg",
    "A7X04324-Edit.jpg",
    "A7X03819-Edit.jpg",
    "A7X03798-Edit.jpg",
    "A7X02510.jpg",
    "A7X01741.jpg",
    "A7X00093.jpg",
    "A7201489.jpg",
    "A7200771-Edit.jpg",
    "A7200678-Edit.jpg",
    "DSC03651.jpg",
    "DSC04045.jpg",
    "DSC03932.jpg",
    "DSC04183.jpg",
    "DSC04148.jpg",
    "DSC04068.jpg",
    "DSC03891.jpg",
    "DSC03988.jpg",
    "DSC02145.jpg",
    "DSC03524.jpg",
    "DSC01414.jpg",
    "DSC04143.jpg",
    "DSC04126.jpg",
    "DSC03771.jpg",
    "DSC03761.jpg",
    "DSC03721.jpg",
    "DSC03731-Pano-Edit.jpg",
    "DSC03233.jpg",
    "DSC03697.jpg",
    "DSC03546.jpg",
    "DSC03152.jpg",
    "DSC02882.jpg",
    "DSC02899.jpg",
    "DSC02618.jpg",
    "DSC02523.jpg",
    "DSC02333.jpg",
    "DSC02325.jpg",
    "DSC01359.jpg",
    "DSC01459.jpg",
    "DSC01348.jpg",
    "A7X05589.jpg",
    "Kids_D2.jpg",
    "IMG_3928.jpg"
  ],
  "collections": {
    "Furry Friends": [
      "Furry Friends/A7X02063.jpg",
      "Furry Friends/A7X01524.jpg",
      "Furry Friends/DSC02230.jpg",
      "Furry Friends/DSC02185.jpg",
      "Furry Friends/DSC02089.jpg",
      "Furry Friends/A7X02492.jpg",
      "Furry Friends/A7X02071.jpg"
    ],
    "Mono": [
      "Mono/A7X02990-Edit.jpg",
      "Mono/A7X02946.jpg",
      "Mono/A7X02723.jpg",
      "Mono/A7X02384.jpg",
      "Mono/A7X07442.jpg",
      "Mono/A7200894-Edit.jpg",
      "Mono/DSC04051.jpg",
      "Mono/DSC04179.jpg",
      "Mono/DSC03997.jpg",
      "Mono/DSC02581.jpg",
      "Mono/DSC03766.jpg",
      "Mono/DSC03920-Edit.jpg",
      "Mono/DSC02593.jpg",
      "Mono/A7X05474.jpg",
      "Mono/Pipes.jpg",
      "Mono/IMG_0534.jpg"
    ],
    "Bong & Mia": [
      "Bong & Mia/DSC02461.jpg",
      "Bong & Mia/DSC02458.jpg"
    ]
  }
}